<ags:resources xmlns:ags="http://purl.org/agmes/1.1/" xmlns:dc="http://purl.org/dc/elements/1.1/" xmlns:agls="http://www.naa.gov.au/recordkeeping/gov_online/agls/1.2" xmlns:dcterms="http://purl.org/dc/terms/">
  <ags:resource ags:ARN="RU2016H10173">
    <dc:title xml:lang="ru">МАТЕРИАЛЫ К ФЛОРЕ ПОЙМЫ РЕКИ ДЕРКУЛ (РЕСПУБЛИКА КАЗАХСТАН)</dc:title>
    <dc:title xml:lang="en">
      <dcterms:alternative>MATERIALS TO THE FLORA FLOODPLAIN OF THE RIVER DERKUL (REPUBLIC OF KAZAKHSTAN)</dcterms:alternative>
    </dc:title>
    <dc:creator>
      <ags:creatorPersonal>ГАГУШКИНА О.М.</ags:creatorPersonal>
    </dc:creator>
    <dc:creator>
      <ags:creatorCorporate>Поволжская государственная социально-гуманитарная академия</ags:creatorCorporate>
    </dc:creator>
    <dc:date>
      <dcterms:dateIssued scheme="dcterms:W3CDTF">2015-</dcterms:dateIssued>
    </dc:date>
    <dc:subject>
      <ags:subjectClassification scheme="ags:ASC">F70</ags:subjectClassification>
    </dc:subject>
    <dc:subject>
      <ags:subjectThesaurus scheme="ags:AGROVOC" xml:lang="en">Flora</ags:subjectThesaurus>
    </dc:subject>
    <dc:subject>
      <ags:subjectThesaurus scheme="ags:AGROVOC" xml:lang="en">analysis</ags:subjectThesaurus>
    </dc:subject>
    <dc:subject>
      <ags:subjectThesaurus scheme="ags:AGROVOC" xml:lang="en">riverbanks</ags:subjectThesaurus>
    </dc:subject>
    <dc:subject>
      <ags:subjectThesaurus scheme="ags:AGROVOC" xml:lang="en">Kazakhstan</ags:subjectThesaurus>
    </dc:subject>
    <dc:subject>
      <ags:subjectThesaurus scheme="ags:AGROVOC">http://aims.fao.org/aos/agrovoc/c_2983</ags:subjectThesaurus>
    </dc:subject>
    <dc:subject>
      <ags:subjectThesaurus scheme="ags:AGROVOC">http://aims.fao.org/aos/agrovoc/c_49928</ags:subjectThesaurus>
    </dc:subject>
    <dc:subject>
      <ags:subjectThesaurus scheme="ags:AGROVOC">http://aims.fao.org/aos/agrovoc/c_25303</ags:subjectThesaurus>
    </dc:subject>
    <dc:subject>
      <ags:subjectThesaurus scheme="ags:AGROVOC">http://aims.fao.org/aos/agrovoc/c_11952</ags:subjectThesaurus>
    </dc:subject>
    <dc:description>
      <dcterms:abstract xml:lang="ru">В статье приводятся данные по анализу флоры левобережной части поймы реки Деркул расположенной в окрестностях г. Уральск, Казахстан.</dcterms:abstract>
    </dc:description>
    <dc:description>
      <dcterms:abstract xml:lang="en">The article presents data on the analysis of flora left bank of the river floodplain Derkul is located in the vicinity of Uralsk, Kazakhstan.</dcterms:abstract>
    </dc:description>
    <dc:identifier scheme="dcterms:URI">http://research-journal.org/wp-content/uploads/2015/03/2-1-33.pdf#page=17</dc:identifier>
    <dc:type>Journal Article</dc:type>
    <dc:language scheme="ags:ISO639-1">ru</dc:language>
    <dc:language scheme="ags:ISO639-1">en</dc:language>
    <ags:citation>
      <ags:citationTitle>Международный научно-исследовательский журнал</ags:citationTitle>
      <ags:citationIdentifier scheme="ags:ISSN">2303-9868</ags:citationIdentifier>
      <ags:citationNumber>v.1/n.2 (33)</ags:citationNumber>
    </ags:citation>
  </ags:resource>
</ags:resources>