<ags:resources xmlns:ags="http://purl.org/agmes/1.1/" xmlns:dc="http://purl.org/dc/elements/1.1/" xmlns:agls="http://www.naa.gov.au/recordkeeping/gov_online/agls/1.2" xmlns:dcterms="http://purl.org/dc/terms/">
  <ags:resource ags:ARN="SK2016017326">
    <dc:title xml:lang="en">Project of Determining Soil Compaction and Soil Water Infiltration Under Impact  of large Herbivores</dc:title>
    <dc:title xml:lang="sk">
      <dcterms:alternative>Vplyv veľkých bylinožravcov na les a pastviny z hľadiska zhutnenia pôdy a rýchlosť infiltrácie vody v strednej a východnej Európe</dcterms:alternative>
    </dc:title>
    <dc:creator>
      <ags:creatorPersonal>Abdelrahman Adam Alfadil Mohammed</ags:creatorPersonal>
    </dc:creator>
    <dc:creator>
      <ags:creatorPersonal>Pichler Viliam</ags:creatorPersonal>
    </dc:creator>
    <dc:creator>
      <ags:creatorCorporate>Technical University in Zvolen, T.G. Masaryka 24, 960 53 Zvolen, Slovak Republic,  email:  pichler@tuzvo.sk</ags:creatorCorporate>
    </dc:creator>
    <dc:date>
      <dcterms:dateIssued scheme="dcterms:W3CDTF">2014-</dcterms:dateIssued>
    </dc:date>
    <dc:subject>
      <ags:subjectClassification scheme="ags:ASC">K01</ags:subjectClassification>
    </dc:subject>
    <dc:subject>
      <ags:subjectThesaurus scheme="ags:AGROVOC" xml:lang="en">herbivores</ags:subjectThesaurus>
    </dc:subject>
    <dc:subject>
      <ags:subjectThesaurus scheme="ags:AGROVOC" xml:lang="en">impact assessment</ags:subjectThesaurus>
    </dc:subject>
    <dc:subject>
      <ags:subjectThesaurus scheme="ags:AGROVOC" xml:lang="en">soil compaction</ags:subjectThesaurus>
    </dc:subject>
    <dc:subject>
      <ags:subjectThesaurus scheme="ags:AGROVOC" xml:lang="en">soil density</ags:subjectThesaurus>
    </dc:subject>
    <dc:subject>
      <ags:subjectThesaurus scheme="ags:AGROVOC" xml:lang="en">soil water</ags:subjectThesaurus>
    </dc:subject>
    <dc:subject>
      <ags:subjectThesaurus scheme="ags:AGROVOC">http://aims.fao.org/aos/agrovoc/c_3567</ags:subjectThesaurus>
    </dc:subject>
    <dc:subject>
      <ags:subjectThesaurus scheme="ags:AGROVOC">http://aims.fao.org/aos/agrovoc/c_37938</ags:subjectThesaurus>
    </dc:subject>
    <dc:subject>
      <ags:subjectThesaurus scheme="ags:AGROVOC">http://aims.fao.org/aos/agrovoc/c_7163</ags:subjectThesaurus>
    </dc:subject>
    <dc:subject>
      <ags:subjectThesaurus scheme="ags:AGROVOC">http://aims.fao.org/aos/agrovoc/c_7167</ags:subjectThesaurus>
    </dc:subject>
    <dc:subject>
      <ags:subjectThesaurus scheme="ags:AGROVOC">http://aims.fao.org/aos/agrovoc/c_7205</ags:subjectThesaurus>
    </dc:subject>
    <dc:description>
      <dcterms:abstract xml:lang="en">The study of impact of large herbivores on forest land and grass land with regard to soil compaction and water infiltration rate was conducted on two main locations are: central and eastern Europe. Central Europe represented by Slovakia which itself includes four study sites are: (Budča -Boky, the Poľana Region (Iviny), Topolčianky Game Reserve, and Kováčovské Kopce (hills). The Eastern Europe location represented by the Bialowieza National Park and the Bialwieza Forest in eastern Poland. The study is aimed to Investigate the physical and hydrophysical effects of large herbivores on soils within silvopastoral system, which caused by trampling or hoof action, with respect to soil compaction, to determine the spatial pattern of influence by grazing animals as well as estimation the rate of soil recovery. samples for determniation of retention curve, bulk density and soil particle density were taken from three kinds of plots represent different sites. Also, Electrical resistivity tomography survey was implemented, for imaging subsurface of the soils. Data were analyized through the use of LLA (loglinear analysis) and LR (logistic regression) models.</dcterms:abstract>
    </dc:description>
    <dc:identifier scheme="dcterms:URI">http://www.tuzvo.sk/files/3_3/Acta_Facultatis_Forestalis/aff_suppll_56_1_2014.pdf</dc:identifier>
    <dc:type>Journal Article</dc:type>
    <dc:language scheme="ags:ISO639-1">en</dc:language>
    <ags:citation>
      <ags:citationTitle>Acta  Facultatis Forestalis Zvolen</ags:citationTitle>
      <ags:citationIdentifier scheme="ags:ISSN">0231-5785</ags:citationIdentifier>
      <ags:citationNumber>v.56/n.Suppl. 1</ags:citationNumber>
    </ags:citation>
  </ags:resource>
</ags:resources>