<ags:resources xmlns:ags="http://purl.org/agmes/1.1/" xmlns:dc="http://purl.org/dc/elements/1.1/" xmlns:agls="http://www.naa.gov.au/recordkeeping/gov_online/agls/1.2" xmlns:dcterms="http://purl.org/dc/terms/">
  <ags:resource ags:ARN="SK2016013211">
    <dc:title xml:lang="en">Noise intensity versus mental stress of man</dc:title>
    <dc:title xml:lang="sk">
      <dcterms:alternative>Intenzita hluku verzus psychická záťaž človeka</dcterms:alternative>
    </dc:title>
    <dc:creator>
      <ags:creatorPersonal>Hnilica Richard</ags:creatorPersonal>
    </dc:creator>
    <dc:creator>
      <ags:creatorPersonal>Dado  Miroslav</ags:creatorPersonal>
    </dc:creator>
    <dc:creator>
      <ags:creatorPersonal>Šoteková Anna</ags:creatorPersonal>
    </dc:creator>
    <dc:creator>
      <ags:creatorCorporate>Technical University in Zvolen, T.G. Masaryka 24, 960 53 Zvolen, Slovak Republic,  email: hnilica@tuzvo.sk</ags:creatorCorporate>
    </dc:creator>
    <dc:date>
      <dcterms:dateIssued scheme="dcterms:W3CDTF">2013-</dcterms:dateIssued>
    </dc:date>
    <dc:subject>
      <ags:subjectClassification scheme="ags:ASC">T10</ags:subjectClassification>
    </dc:subject>
    <dc:subject>
      <ags:subjectThesaurus scheme="ags:AGROVOC" xml:lang="en">working conditions</ags:subjectThesaurus>
    </dc:subject>
    <dc:subject>
      <ags:subjectThesaurus scheme="ags:AGROVOC" xml:lang="en">Noise</ags:subjectThesaurus>
    </dc:subject>
    <dc:subject>
      <ags:subjectThesaurus scheme="ags:AGROVOC" xml:lang="en">Stress</ags:subjectThesaurus>
    </dc:subject>
    <dc:subject>
      <ags:subjectThesaurus scheme="ags:AGROVOC" xml:lang="en">experimentation</ags:subjectThesaurus>
    </dc:subject>
    <dc:subject>
      <ags:subjectThesaurus scheme="ags:AGROVOC">http://aims.fao.org/aos/agrovoc/c_8448</ags:subjectThesaurus>
    </dc:subject>
    <dc:subject>
      <ags:subjectThesaurus scheme="ags:AGROVOC">http://aims.fao.org/aos/agrovoc/c_5205</ags:subjectThesaurus>
    </dc:subject>
    <dc:subject>
      <ags:subjectThesaurus scheme="ags:AGROVOC">http://aims.fao.org/aos/agrovoc/c_7452</ags:subjectThesaurus>
    </dc:subject>
    <dc:subject>
      <ags:subjectThesaurus scheme="ags:AGROVOC">http://aims.fao.org/aos/agrovoc/c_2758</ags:subjectThesaurus>
    </dc:subject>
    <dc:description>
      <dcterms:abstract xml:lang="en">In general, noise can be considered as one of the most frequent risk factors, which influences the human comfort at work. It is therefore possible to say that the noise intensity will largely influence the mental stress of man at work. The submitted paper by means of experiment carried out analysis of the negative effects of noise on human mental stress according to noise intensity.</dcterms:abstract>
    </dc:description>
    <dc:identifier scheme="dcterms:URI">http://www.tuzvo.sk/files/FEVT/fakulta_fevt/akta_fevt-2-2013-hnilica.pdf</dc:identifier>
    <dc:type>Journal Article</dc:type>
    <dc:language scheme="ags:ISO639-1">sk</dc:language>
    <ags:citation>
      <ags:citationTitle>Acta facultatis technicae Zvolen</ags:citationTitle>
      <ags:citationIdentifier scheme="ags:ISSN">1336-4472</ags:citationIdentifier>
      <ags:citationNumber>v.18/n.2</ags:citationNumber>
    </ags:citation>
  </ags:resource>
</ags:resources>