<ags:resources xmlns:ags="http://purl.org/agmes/1.1/" xmlns:dc="http://purl.org/dc/elements/1.1/" xmlns:agls="http://www.naa.gov.au/recordkeeping/gov_online/agls/1.2" xmlns:dcterms="http://purl.org/dc/terms/">
  <ags:resource ags:ARN="GE2016007352">
    <dc:title xml:lang="en">Biological and physico-chemical properties of X. Phaseoli specific phages</dc:title>
    <dc:creator>
      <ags:creatorPersonal>Sadunishvili T.A.</ags:creatorPersonal>
    </dc:creator>
    <dc:creator>
      <ags:creatorPersonal>Gamkrelidze M.D.</ags:creatorPersonal>
    </dc:creator>
    <dc:creator>
      <ags:creatorPersonal>Gaganidze D.L.</ags:creatorPersonal>
    </dc:creator>
    <dc:creator>
      <ags:creatorPersonal>Amashukeli N.V.</ags:creatorPersonal>
    </dc:creator>
    <dc:date>
      <dcterms:dateIssued scheme="dcterms:W3CDTF">2014-</dcterms:dateIssued>
    </dc:date>
    <dc:subject>
      <ags:subjectClassification scheme="ags:ASC">F60</ags:subjectClassification>
    </dc:subject>
    <dc:subject>
      <ags:subjectThesaurus scheme="ags:AGROVOC" xml:lang="en">Phages</ags:subjectThesaurus>
    </dc:subject>
    <dc:subject>
      <ags:subjectThesaurus scheme="ags:AGROVOC" xml:lang="en">Chemicophysical properties</ags:subjectThesaurus>
    </dc:subject>
    <dc:subject>
      <ags:subjectThesaurus scheme="ags:AGROVOC" xml:lang="en">adsorption</ags:subjectThesaurus>
    </dc:subject>
    <dc:subject>
      <ags:subjectThesaurus scheme="ags:AGROVOC" xml:lang="en">Xanthomonas campestris phaseoli</ags:subjectThesaurus>
    </dc:subject>
    <dc:subject>
      <ags:subjectThesaurus scheme="ags:AGROVOC">http://aims.fao.org/aos/agrovoc/c_13274</ags:subjectThesaurus>
    </dc:subject>
    <dc:subject>
      <ags:subjectThesaurus scheme="ags:AGROVOC">http://aims.fao.org/aos/agrovoc/c_1521</ags:subjectThesaurus>
    </dc:subject>
    <dc:subject>
      <ags:subjectThesaurus scheme="ags:AGROVOC">http://aims.fao.org/aos/agrovoc/c_137</ags:subjectThesaurus>
    </dc:subject>
    <dc:subject>
      <ags:subjectThesaurus scheme="ags:AGROVOC">http://aims.fao.org/aos/agrovoc/c_36124</ags:subjectThesaurus>
    </dc:subject>
    <dc:description>
      <dcterms:abstract xml:lang="en">Some biological and physical/chemical properties of the three lines of lytic bacteriophages specific for Xan- thomonas phaseoli causing haricot brown spot in Georgia was studied. The bacteriophages belong to the Tailed phages, family Myoviridae. The adsorption time and latent period were short and nearly identical for the three phages. Influence of solution of blue vitriol and copper oxychloride to phages mixture was studied. Influence of high temperature on the phages and their mixture was investigated. It was found that tested bacteriophages belong to the high temperature resistant phages.</dcterms:abstract>
    </dc:description>
    <dc:identifier scheme="dcterms:URI">http://agrscience.ge/</dc:identifier>
    <dc:type>Journal Article</dc:type>
    <ags:citation>
      <ags:citationTitle>Annals of agrarian science</ags:citationTitle>
      <ags:citationIdentifier scheme="ags:ISSN">1512-1887</ags:citationIdentifier>
      <ags:citationNumber>v.12/n.3</ags:citationNumber>
    </ags:citation>
  </ags:resource>
</ags:resources>