<ags:resources xmlns:ags="http://purl.org/agmes/1.1/" xmlns:dc="http://purl.org/dc/elements/1.1/" xmlns:agls="http://www.naa.gov.au/recordkeeping/gov_online/agls/1.2" xmlns:dcterms="http://purl.org/dc/terms/">
  <ags:resource ags:ARN="RU2016204823">
    <dc:title xml:lang="en">FARMER’S PROFITABILITY OF POTATO CULTIVATION AT RANGPUR DISTRICT: THE SOCIO-ECONOMIC CONTEXT OF BANGLADESH</dc:title>
    <dc:creator>
      <ags:creatorPersonal>Mukul Abu Zafar Ahmed</ags:creatorPersonal>
    </dc:creator>
    <dc:creator>
      <ags:creatorPersonal>Rayhan Shah Johir</ags:creatorPersonal>
    </dc:creator>
    <dc:creator>
      <ags:creatorPersonal>Hassan Masudul</ags:creatorPersonal>
    </dc:creator>
    <dc:creator>
      <ags:creatorCorporate>Great Zimbabwe University, Masvingo, Zimbabwe</ags:creatorCorporate>
    </dc:creator>
    <dc:date>
      <dcterms:dateIssued scheme="dcterms:W3CDTF">2013-</dcterms:dateIssued>
    </dc:date>
    <dc:subject>
      <ags:subjectClassification scheme="ags:ASC">E10</ags:subjectClassification>
    </dc:subject>
    <dc:subject>
      <ags:subjectThesaurus scheme="ags:AGROVOC" xml:lang="en">Gross national product</ags:subjectThesaurus>
    </dc:subject>
    <dc:subject>
      <ags:subjectThesaurus scheme="ags:AGROVOC" xml:lang="en">Food crops</ags:subjectThesaurus>
    </dc:subject>
    <dc:subject>
      <ags:subjectThesaurus scheme="ags:AGROVOC" xml:lang="en">Bangladesh</ags:subjectThesaurus>
    </dc:subject>
    <dc:subject>
      <ags:subjectThesaurus scheme="ags:AGROVOC" xml:lang="en">Cash crops</ags:subjectThesaurus>
    </dc:subject>
    <dc:subject>
      <ags:subjectThesaurus scheme="ags:AGROVOC" xml:lang="en">Developing countries</ags:subjectThesaurus>
    </dc:subject>
    <dc:subject>
      <ags:subjectThesaurus scheme="ags:AGROVOC" xml:lang="en">foods</ags:subjectThesaurus>
    </dc:subject>
    <dc:subject>
      <ags:subjectThesaurus scheme="ags:AGROVOC" xml:lang="en">Production data</ags:subjectThesaurus>
    </dc:subject>
    <dc:subject>
      <ags:subjectThesaurus scheme="ags:AGROVOC" xml:lang="en">Markets</ags:subjectThesaurus>
    </dc:subject>
    <dc:subject>
      <ags:subjectThesaurus scheme="ags:AGROVOC" xml:lang="en">Prices</ags:subjectThesaurus>
    </dc:subject>
    <dc:subject>
      <ags:subjectThesaurus scheme="ags:AGROVOC" xml:lang="en">storage</ags:subjectThesaurus>
    </dc:subject>
    <dc:subject>
      <ags:subjectThesaurus scheme="ags:AGROVOC">http://aims.fao.org/aos/agrovoc/c_11364</ags:subjectThesaurus>
    </dc:subject>
    <dc:subject>
      <ags:subjectThesaurus scheme="ags:AGROVOC">http://aims.fao.org/aos/agrovoc/c_3017</ags:subjectThesaurus>
    </dc:subject>
    <dc:subject>
      <ags:subjectThesaurus scheme="ags:AGROVOC">http://aims.fao.org/aos/agrovoc/c_810</ags:subjectThesaurus>
    </dc:subject>
    <dc:subject>
      <ags:subjectThesaurus scheme="ags:AGROVOC">http://aims.fao.org/aos/agrovoc/c_1359</ags:subjectThesaurus>
    </dc:subject>
    <dc:subject>
      <ags:subjectThesaurus scheme="ags:AGROVOC">http://aims.fao.org/aos/agrovoc/c_2222</ags:subjectThesaurus>
    </dc:subject>
    <dc:subject>
      <ags:subjectThesaurus scheme="ags:AGROVOC">http://aims.fao.org/aos/agrovoc/c_3032</ags:subjectThesaurus>
    </dc:subject>
    <dc:subject>
      <ags:subjectThesaurus scheme="ags:AGROVOC">http://aims.fao.org/aos/agrovoc/c_32548</ags:subjectThesaurus>
    </dc:subject>
    <dc:subject>
      <ags:subjectThesaurus scheme="ags:AGROVOC">http://aims.fao.org/aos/agrovoc/c_4626</ags:subjectThesaurus>
    </dc:subject>
    <dc:subject>
      <ags:subjectThesaurus scheme="ags:AGROVOC">http://aims.fao.org/aos/agrovoc/c_6178</ags:subjectThesaurus>
    </dc:subject>
    <dc:subject>
      <ags:subjectThesaurus scheme="ags:AGROVOC">http://aims.fao.org/aos/agrovoc/c_7427</ags:subjectThesaurus>
    </dc:subject>
    <dc:description>
      <dcterms:abstract xml:lang="en">Bangladesh is predominantly an agricultural country. Agriculture is the indispensable culture of Bangladesh. Agriculture has a enceinte contribution to the Gross Domestic Product (GDP) of the country. Earlier more than 50% of GDP came from this sector. Various types of crops are produced in this country. These crops might have been categorized into two-food crops and cash crops. Potato is one of the food-stuff of the most people of the world as well as Bangladesh. Potato crop is being treated as foremost crop. This study was conducted to approximation the cost of production and profitability of potato producers at Rangpur district. Data collected from 30 farmers using simple random sampling technique. The potato farmers showed individual differences in their socio-economic characteristics and absolute majority of them belonged to young age category (20-35 years) having medium family size, illiterate, medium farm size (0.34-1.0 acre), (1-10 years) farming experience. Most of the respondents used cardinal variety of potato seed and sell their output at home. Farmers who sell potato in the market were more profitable than others. The study also designates that the large farmers were most profitable compared to others. Major problem faced by the potato farmers were lower price of potato during harvesting period, price fluctuation , shortage of capital, high charge of cold storage, lack of good quality seed, perish ability of potato, poor storage facility, higher price of inputs and lack of marketing facility etc. Proper steps should be postulated by Government to puzzle out this problem. The determinations of the study will generate basic economic data on the production practices of potato. At long last it will be helpful to the planners and policy makers in contriving micro or macro level policy for the enlargement of potato production in the country.</dcterms:abstract>
    </dc:description>
    <dc:identifier scheme="dcterms:URI">http://www.rjoas.com/issue-2013-07/article_03.pdf</dc:identifier>
    <dc:type>Journal Article</dc:type>
    <dc:language scheme="ags:ISO639-1">en</dc:language>
    <ags:citation>
      <ags:citationTitle>Russian Journal of Agricultural and Socio-Economic Sciences</ags:citationTitle>
      <ags:citationIdentifier scheme="ags:ISSN">2226-1184</ags:citationIdentifier>
      <ags:citationNumber>v.19/n.7</ags:citationNumber>
    </ags:citation>
  </ags:resource>
</ags:resources>