<ags:resources xmlns:ags="http://purl.org/agmes/1.1/" xmlns:dc="http://purl.org/dc/elements/1.1/" xmlns:agls="http://www.naa.gov.au/recordkeeping/gov_online/agls/1.2" xmlns:dcterms="http://purl.org/dc/terms/">
  <ags:resource ags:ARN="RU2016204800">
    <dc:title xml:lang="en">SOIL PROPERTIES DYNAMICS INDUCED BY PASSAGE OF FIRE DURING AGRICULTURAL BURNING</dc:title>
    <dc:creator>
      <ags:creatorPersonal>Dennis Edem I.</ags:creatorPersonal>
    </dc:creator>
    <dc:creator>
      <ags:creatorPersonal>Usoroh Alphonsus D.</ags:creatorPersonal>
    </dc:creator>
    <dc:creator>
      <ags:creatorPersonal>Essien Rosemary A.</ags:creatorPersonal>
    </dc:creator>
    <dc:creator>
      <ags:creatorCorporate>University o f Uyo, Nigeria</ags:creatorCorporate>
    </dc:creator>
    <dc:creator>
      <ags:creatorCorporate>Akwa Ibom State University, Nigeria</ags:creatorCorporate>
    </dc:creator>
    <dc:date>
      <dcterms:dateIssued scheme="dcterms:W3CDTF">2013-</dcterms:dateIssued>
    </dc:date>
    <dc:subject>
      <ags:subjectClassification scheme="ags:ASC">F07</ags:subjectClassification>
    </dc:subject>
    <dc:subject>
      <ags:subjectThesaurus scheme="ags:AGROVOC" xml:lang="en">Soil</ags:subjectThesaurus>
    </dc:subject>
    <dc:subject>
      <ags:subjectThesaurus scheme="ags:AGROVOC" xml:lang="en">Standards</ags:subjectThesaurus>
    </dc:subject>
    <dc:subject>
      <ags:subjectThesaurus scheme="ags:AGROVOC" xml:lang="en">chemical composition</ags:subjectThesaurus>
    </dc:subject>
    <dc:subject>
      <ags:subjectThesaurus scheme="ags:AGROVOC" xml:lang="en">Carbon</ags:subjectThesaurus>
    </dc:subject>
    <dc:subject>
      <ags:subjectThesaurus scheme="ags:AGROVOC" xml:lang="en">Fires</ags:subjectThesaurus>
    </dc:subject>
    <dc:subject>
      <ags:subjectThesaurus scheme="ags:AGROVOC" xml:lang="en">Quality</ags:subjectThesaurus>
    </dc:subject>
    <dc:subject>
      <ags:subjectThesaurus scheme="ags:AGROVOC" xml:lang="en">Soil structural units</ags:subjectThesaurus>
    </dc:subject>
    <dc:subject>
      <ags:subjectThesaurus scheme="ags:AGROVOC" xml:lang="en">Soil temperature</ags:subjectThesaurus>
    </dc:subject>
    <dc:subject>
      <ags:subjectThesaurus scheme="ags:AGROVOC" xml:lang="en">pH</ags:subjectThesaurus>
    </dc:subject>
    <dc:subject>
      <ags:subjectThesaurus scheme="ags:AGROVOC" xml:lang="en">Burning</ags:subjectThesaurus>
    </dc:subject>
    <dc:subject>
      <ags:subjectThesaurus scheme="ags:AGROVOC">http://aims.fao.org/aos/agrovoc/c_7156</ags:subjectThesaurus>
    </dc:subject>
    <dc:subject>
      <ags:subjectThesaurus scheme="ags:AGROVOC">http://aims.fao.org/aos/agrovoc/c_7367</ags:subjectThesaurus>
    </dc:subject>
    <dc:subject>
      <ags:subjectThesaurus scheme="ags:AGROVOC">http://aims.fao.org/aos/agrovoc/c_1794</ags:subjectThesaurus>
    </dc:subject>
    <dc:subject>
      <ags:subjectThesaurus scheme="ags:AGROVOC">http://aims.fao.org/aos/agrovoc/c_1301</ags:subjectThesaurus>
    </dc:subject>
    <dc:subject>
      <ags:subjectThesaurus scheme="ags:AGROVOC">http://aims.fao.org/aos/agrovoc/c_2915</ags:subjectThesaurus>
    </dc:subject>
    <dc:subject>
      <ags:subjectThesaurus scheme="ags:AGROVOC">http://aims.fao.org/aos/agrovoc/c_6400</ags:subjectThesaurus>
    </dc:subject>
    <dc:subject>
      <ags:subjectThesaurus scheme="ags:AGROVOC">http://aims.fao.org/aos/agrovoc/c_7195</ags:subjectThesaurus>
    </dc:subject>
    <dc:subject>
      <ags:subjectThesaurus scheme="ags:AGROVOC">http://aims.fao.org/aos/agrovoc/c_7197</ags:subjectThesaurus>
    </dc:subject>
    <dc:subject>
      <ags:subjectThesaurus scheme="ags:AGROVOC" />
    </dc:subject>
    <dc:subject>
      <ags:subjectThesaurus scheme="ags:AGROVOC">http://aims.fao.org/aos/agrovoc/c_9499</ags:subjectThesaurus>
    </dc:subject>
    <dc:description>
      <dcterms:abstract xml:lang="en">Characteristics of an ecosystem are altered both as sudden modifications induced by the passage of the fire and the delayed changes derived from the simultaneous modifications of various soil physical and chemical parameters. Effects of fire on soil properties was performed in experimental plots, whose fuel amount was altered in order to obtain different heating intensities with the aim of determining changes in the soil physico-chemical parameters at varying heating temperatures. The research was conducted in a continuous cropped arable experimental plots located at the University of Uyo Teaching and Research Farm (UUTRF), Use-Offot, Uyo, Nigeria for four growing seasons, between March, 2010 to October, 2011. Core and bulk samples from the burned and adjacent unburned plots (control) were collected for physico-chemical analysis using standard procedures. These induced temperatures were highly variable on the soil surface. Temperature differences significantly (P &lt; 0.05) affected sand, total nitrogen, organic carbon and pH contents of the soils positively (r = 0.518, 0.478, 0.582, 0.595 respectively), whereas a reduction in the soil temperature increased the concentrations of clay, 1mm, 0.05mm and 0.25 mm stable soil aggregates in the soil (r = -0.619, -0.578, -0.780, -0.526 respectively) after burning. Exchange acidity increased to 5.12 cmolkg-1 at 400C from 0.80 cmolkg-1 at initial temperature of 250C at the surface soil. Though aggregates formation was significantly higher (P = 0.05) after burning than the control soil locations, this soil will easily be distressed with the least application of force. The pH decreased to 5.4 at higher temperatures following burning before ashes mineralized. However, both organic matter and ECEC increased at increasing soil temperature. Potassium content remained surprisingly constant as the soil temperature increased. Despite the merits of quick release of occluded nutrients, heating temperatures of slash-and-burn method of land clearing altered soil quality attributes.</dcterms:abstract>
    </dc:description>
    <dc:identifier scheme="dcterms:URI">http://www.rjoas.com/issue-2013-05/article_04.pdf</dc:identifier>
    <dc:type>Journal Article</dc:type>
    <dc:language scheme="ags:ISO639-1">en</dc:language>
    <ags:citation>
      <ags:citationTitle>Russian Journal of Agricultural and Socio-Economic Sciences</ags:citationTitle>
      <ags:citationIdentifier scheme="ags:ISSN">2226-1184</ags:citationIdentifier>
      <ags:citationNumber>v.17/n.5</ags:citationNumber>
    </ags:citation>
  </ags:resource>
</ags:resources>